[
  {
    "tags": [
      {
        "tag": {
          "display_name": "Tag1",
          "uuid": "5e0c6396-aa0d-48ed-ac06-3a16cdd6286d",
          "name": "Application-Green",
          "href": "http://10.84.17.3:8082/tag/5e0c6396-aa0d-48ed-ac06-3a16cdd6286d",
          "tag_id": 134217737,
          "tag_value": "Green",
          "perms2": {
            "owner": "cloud-admin",
            "owner_access": 7,
            "global_access": 0,
            "share": []
          },
          "id_perms": {
            "enable": true,
            "uuid": {
              "uuid_mslong": 6776901038034995000,
              "uuid_lslong": 12395658894000925000
            },
            "created": "2017-05-20T13:45:13.471414",
            "description": null,
            "creator": null,
            "user_visible": true,
            "last_modified": "2017-05-20T13:45:13.471414",
            "permissions": {
              "owner": "cloud-admin",
              "owner_access": 7,
              "other_access": 7,
              "group": "cloud-admin-group",
              "group_access": 7
            }
          },
          "fq_name": [
            "Application-Green"
          ],
          "tag_type": "Application"
        }
      },
      {
        "tag": {
          "display_name": "HR",
          "uuid": "b7b15339-6ffc-48f5-b971-2697602f0665",
          "name": "Application-HR",
          "href": "http://10.84.17.3:8082/tag/b7b15339-6ffc-48f5-b971-2697602f0665",
          "tag_id": 134217773,
          "tag_value": "HR",
          "perms2": {
            "owner": "cloud-admin",
            "owner_access": 7,
            "global_access": 0,
            "share": []
          },
          "id_perms": {
            "enable": true,
            "uuid": {
              "uuid_mslong": 13236452285975644000,
              "uuid_lslong": 13362504000980584000
            },
            "created": "2017-05-23T14:06:09.317447",
            "description": null,
            "creator": null,
            "user_visible": true,
            "last_modified": "2017-05-23T14:06:09.317447",
            "permissions": {
              "owner": "cloud-admin",
              "owner_access": 7,
              "other_access": 7,
              "group": "cloud-admin-group",
              "group_access": 7
            }
          },
          "fq_name": [
            "Application-HR"
          ],
          "tag_type": "Application"
        }
      },
      {
        "tag": {
          "display_name": "Label-mylabel2",
          "uuid": "3f749fad-1f55-4a9a-8243-ed9a6326711d",
          "name": "Label-mylabel2",
          "href": "http://10.84.17.3:8082/tag/3f749fad-1f55-4a9a-8243-ed9a6326711d",
          "perms2": {
            "owner": "cloud-admin",
            "owner_access": 7,
            "global_access": 0,
            "share": []
          },
          "tag_value": "mylabel2",
          "id_perms": {
            "enable": true,
            "uuid": {
              "uuid_mslong": 4572455087591738000,
              "uuid_lslong": 9386607295714456000
            },
            "created": "2017-05-23T12:01:24.553386",
            "description": null,
            "creator": null,
            "user_visible": true,
            "last_modified": "2017-05-23T12:01:24.553386",
            "permissions": {
              "owner": "cloud-admin",
              "owner_access": 7,
              "other_access": 7,
              "group": "cloud-admin-group",
              "group_access": 7
            }
          },
          "tag_id": 42,
          "fq_name": [
            "Label-mylabel2"
          ],
          "tag_type": "Label"
        }
      },
      {
        "tag": {
          "display_name": "Tag10",
          "uuid": "fb561368-3297-49a6-98f6-1b890d25026c",
          "name": "Label-10",
          "href": "http://10.84.17.3:8082/tag/fb561368-3297-49a6-98f6-1b890d25026c",
          "perms2": {
            "owner": "cloud-admin",
            "owner_access": 7,
            "global_access": 0,
            "share": []
          },
          "tag_value": "10",
          "id_perms": {
            "enable": true,
            "uuid": {
              "uuid_mslong": 18110684289763330000,
              "uuid_lslong": 11022027413480866000
            },
            "created": "2017-05-24T08:17:51.460625",
            "description": null,
            "creator": null,
            "user_visible": true,
            "last_modified": "2017-05-24T08:17:51.460625",
            "permissions": {
              "owner": "cloud-admin",
              "owner_access": 7,
              "other_access": 7,
              "group": "cloud-admin-group",
              "group_access": 7
            }
          },
          "tag_id": 52,
          "fq_name": [
            "Label-10"
          ],
          "tag_type": "Label"
        }
      },
      {
        "tag": {
          "display_name": "Tier-UI",
          "uuid": "205c072e-2827-4908-b23e-141e49839877",
          "name": "Tier-UI",
          "href": "http://10.84.17.3:8082/tag/205c072e-2827-4908-b23e-141e49839877",
          "perms2": {
            "owner": "cloud-admin",
            "owner_access": 7,
            "global_access": 0,
            "share": []
          },
          "tag_value": "UI",
          "id_perms": {
            "enable": true,
            "uuid": {
              "uuid_mslong": 2331746601894628000,
              "uuid_lslong": 12843725307622169000
            },
            "created": "2017-05-24T11:37:21.568695",
            "description": null,
            "creator": null,
            "user_visible": true,
            "last_modified": "2017-05-24T11:37:21.568695",
            "permissions": {
              "owner": "cloud-admin",
              "owner_access": 7,
              "other_access": 7,
              "group": "cloud-admin-group",
              "group_access": 7
            }
          },
          "tag_id": 268435509,
          "fq_name": [
            "Tier-UI"
          ],
          "tag_type": "Tier"
        }
      },
      {
        "tag": {
          "display_name": "Tap1",
          "uuid": "7464f0cd-9ff6-4e9d-9492-176e06a69fda",
          "name": "Label-1",
          "href": "http://10.84.17.3:8082/tag/7464f0cd-9ff6-4e9d-9492-176e06a69fda",
          "perms2": {
            "owner": "cloud-admin",
            "owner_access": 7,
            "global_access": 0,
            "share": []
          },
          "tag_value": "1",
          "id_perms": {
            "enable": true,
            "uuid": {
              "uuid_mslong": 8387093172013388000,
              "uuid_lslong": 10705645025538515000
            },
            "created": "2017-05-24T07:58:15.826132",
            "description": null,
            "creator": null,
            "user_visible": true,
            "last_modified": "2017-05-24T07:58:15.826132",
            "permissions": {
              "owner": "cloud-admin",
              "owner_access": 7,
              "other_access": 7,
              "group": "cloud-admin-group",
              "group_access": 7
            }
          },
          "tag_id": 48,
          "fq_name": [
            "Label-1"
          ],
          "tag_type": "Label"
        }
      },
      {
        "tag": {
          "display_name": "App10",
          "uuid": "8d1bbbb6-c88a-453a-ad4b-6c93c2ba7ca7",
          "name": "Application-3",
          "href": "http://10.84.17.3:8082/tag/8d1bbbb6-c88a-453a-ad4b-6c93c2ba7ca7",
          "perms2": {
            "owner": "cloud-admin",
            "owner_access": 7,
            "global_access": 0,
            "share": []
          },
          "tag_value": "3",
          "id_perms": {
            "enable": true,
            "uuid": {
              "uuid_mslong": 10167926977441974000,
              "uuid_lslong": 12487193773697827000
            },
            "created": "2017-05-24T08:02:26.254859",
            "description": null,
            "creator": null,
            "user_visible": true,
            "last_modified": "2017-05-24T08:02:26.254859",
            "permissions": {
              "owner": "cloud-admin",
              "owner_access": 7,
              "other_access": 7,
              "group": "cloud-admin-group",
              "group_access": 7
            }
          },
          "tag_id": 134217779,
          "fq_name": [
            "Application-3"
          ],
          "tag_type": "Application"
        }
      },
      {
        "tag": {
          "display_name": "Tag1",
          "uuid": "df31388d-11b0-4970-9dfb-f39edbf57079",
          "name": "Site-Bangalore",
          "href": "http://10.84.17.3:8082/tag/df31388d-11b0-4970-9dfb-f39edbf57079",
          "tag_id": 536870922,
          "tag_value": "Bangalore",
          "perms2": {
            "owner": "cloud-admin",
            "owner_access": 7,
            "global_access": 0,
            "share": []
          },
          "id_perms": {
            "enable": true,
            "uuid": {
              "uuid_mslong": 16082697922855062000,
              "uuid_lslong": 11383960346729738000
            },
            "created": "2017-05-20T13:45:26.755983",
            "description": null,
            "creator": null,
            "user_visible": true,
            "last_modified": "2017-05-20T13:45:26.755983",
            "permissions": {
              "owner": "cloud-admin",
              "owner_access": 7,
              "other_access": 7,
              "group": "cloud-admin-group",
              "group_access": 7
            }
          },
          "fq_name": [
            "Site-Bangalore"
          ],
          "tag_type": "Site"
        }
      },
      {
        "tag": {
          "display_name": "Tap3",
          "uuid": "d6047b0d-d2c4-43c3-89bc-bee0fabe8766",
          "name": "Label-3",
          "href": "http://10.84.17.3:8082/tag/d6047b0d-d2c4-43c3-89bc-bee0fabe8766",
          "perms2": {
            "owner": "cloud-admin",
            "owner_access": 7,
            "global_access": 0,
            "share": []
          },
          "tag_value": "3",
          "id_perms": {
            "enable": true,
            "uuid": {
              "uuid_mslong": 15421586323324290000,
              "uuid_lslong": 9925017552306473000
            },
            "created": "2017-05-24T07:58:32.903582",
            "description": null,
            "creator": null,
            "user_visible": true,
            "last_modified": "2017-05-24T07:58:32.903582",
            "permissions": {
              "owner": "cloud-admin",
              "owner_access": 7,
              "other_access": 7,
              "group": "cloud-admin-group",
              "group_access": 7
            }
          },
          "tag_id": 50,
          "fq_name": [
            "Label-3"
          ],
          "tag_type": "Label"
        }
      },
      {
        "tag": {
          "display_name": "Tap2",
          "uuid": "da0d8e84-d4a1-4705-a7e7-c5cef3197f13",
          "name": "Label-2",
          "href": "http://10.84.17.3:8082/tag/da0d8e84-d4a1-4705-a7e7-c5cef3197f13",
          "perms2": {
            "owner": "cloud-admin",
            "owner_access": 7,
            "global_access": 0,
            "share": []
          },
          "tag_value": "2",
          "id_perms": {
            "enable": true,
            "uuid": {
              "uuid_mslong": 15712371376119695000,
              "uuid_lslong": 12098856416586596000
            },
            "created": "2017-05-24T07:58:25.579025",
            "description": null,
            "creator": null,
            "user_visible": true,
            "last_modified": "2017-05-24T07:58:25.579025",
            "permissions": {
              "owner": "cloud-admin",
              "owner_access": 7,
              "other_access": 7,
              "group": "cloud-admin-group",
              "group_access": 7
            }
          },
          "tag_id": 49,
          "fq_name": [
            "Label-2"
          ],
          "tag_type": "Label"
        }
      },
      {
        "tag": {
          "display_name": "Application-Red",
          "uuid": "b0b0c06d-9164-4820-8e06-c586e064e8bc",
          "name": "Application-Red",
          "href": "http://10.84.17.3:8082/tag/b0b0c06d-9164-4820-8e06-c586e064e8bc",
          "parent_uuid": "fb339563-f93a-4418-bb4d-62f8d5a11c0b",
          "parent_type": "project",
          "tag_id": 134217762,
          "tag_value": "Red",
          "perms2": {
            "owner": "cloud-admin",
            "owner_access": 7,
            "global_access": 0,
            "share": []
          },
          "id_perms": {
            "enable": true,
            "uuid": {
              "uuid_mslong": 12731887723399629000,
              "uuid_lslong": 10234084386327030000
            },
            "created": "2017-05-23T05:06:34.326011",
            "description": null,
            "creator": null,
            "user_visible": true,
            "last_modified": "2017-05-23T05:06:34.326011",
            "permissions": {
              "owner": "cloud-admin",
              "owner_access": 7,
              "other_access": 7,
              "group": "cloud-admin-group",
              "group_access": 7
            }
          },
          "fq_name": [
            "default-domain",
            "admin",
            "Application-Red"
          ],
          "tag_type": "Application"
        }
      },
      {
        "tag": {
          "display_name": "Site-Sunnyvale",
          "uuid": "4eaf750d-756c-4ff5-8732-767b3398af0a",
          "name": "Site-Sunnyvale",
          "href": "http://10.84.17.3:8082/tag/4eaf750d-756c-4ff5-8732-767b3398af0a",
          "parent_uuid": "fb339563-f93a-4418-bb4d-62f8d5a11c0b",
          "parent_type": "project",
          "tag_id": 536870943,
          "tag_value": "Sunnyvale",
          "perms2": {
            "owner": "cloud-admin",
            "owner_access": 7,
            "global_access": 0,
            "share": []
          },
          "id_perms": {
            "enable": true,
            "uuid": {
              "uuid_mslong": 5669879156547801000,
              "uuid_lslong": 9741979215474504000
            },
            "created": "2017-05-22T09:32:53.066639",
            "description": null,
            "creator": null,
            "user_visible": true,
            "last_modified": "2017-05-22T09:32:53.066639",
            "permissions": {
              "owner": "cloud-admin",
              "owner_access": 7,
              "other_access": 7,
              "group": "cloud-admin-group",
              "group_access": 7
            }
          },
          "fq_name": [
            "default-domain",
            "admin",
            "Site-Sunnyvale"
          ],
          "tag_type": "Site"
        }
      },
      {
        "tag": {
          "display_name": "Site-",
          "uuid": "fc6f5c5e-1672-43a1-9bbf-76c2cca90f0a",
          "name": "Site-",
          "href": "http://10.84.17.3:8082/tag/fc6f5c5e-1672-43a1-9bbf-76c2cca90f0a",
          "parent_uuid": "fb339563-f93a-4418-bb4d-62f8d5a11c0b",
          "parent_type": "project",
          "tag_id": 536870966,
          "tag_value": "",
          "perms2": {
            "owner": "cloud-admin",
            "owner_access": 7,
            "global_access": 0,
            "share": []
          },
          "id_perms": {
            "enable": true,
            "uuid": {
              "uuid_mslong": 18189858979145990000,
              "uuid_lslong": 11222819375459930000
            },
            "created": "2017-05-25T03:04:08.189220",
            "description": null,
            "creator": null,
            "user_visible": true,
            "last_modified": "2017-05-25T03:04:08.189220",
            "permissions": {
              "owner": "cloud-admin",
              "owner_access": 7,
              "other_access": 7,
              "group": "cloud-admin-group",
              "group_access": 7
            }
          },
          "fq_name": [
            "default-domain",
            "admin",
            "Site-"
          ],
          "tag_type": "Site"
        }
      },
      {
        "tag": {
          "display_name": "Label-mylabel1",
          "uuid": "34fa982a-5d5d-47be-b4d0-c8ddc4aa9002",
          "name": "Label-mylabel1",
          "href": "http://10.84.17.3:8082/tag/34fa982a-5d5d-47be-b4d0-c8ddc4aa9002",
          "perms2": {
            "owner": "cloud-admin",
            "owner_access": 7,
            "global_access": 0,
            "share": []
          },
          "tag_value": "mylabel1",
          "id_perms": {
            "enable": true,
            "uuid": {
              "uuid_mslong": 3817530941872359400,
              "uuid_lslong": 13029134576795685000
            },
            "created": "2017-05-23T12:00:38.498517",
            "description": null,
            "creator": null,
            "user_visible": true,
            "last_modified": "2017-05-23T12:00:38.498517",
            "permissions": {
              "owner": "cloud-admin",
              "owner_access": 7,
              "other_access": 7,
              "group": "cloud-admin-group",
              "group_access": 7
            }
          },
          "tag_id": 41,
          "fq_name": [
            "Label-mylabel1"
          ],
          "tag_type": "Label"
        }
      },
      {
        "tag": {
          "display_name": "Label-Label1",
          "uuid": "0aecdc82-4e47-465e-803a-0cf890052e07",
          "name": "Label-Label1",
          "href": "http://10.84.17.3:8082/tag/0aecdc82-4e47-465e-803a-0cf890052e07",
          "parent_uuid": "fb339563-f93a-4418-bb4d-62f8d5a11c0b",
          "parent_type": "project",
          "tag_id": 35,
          "tag_value": "Label1",
          "perms2": {
            "owner": "cloud-admin",
            "owner_access": 7,
            "global_access": 0,
            "share": []
          },
          "id_perms": {
            "enable": true,
            "uuid": {
              "uuid_mslong": 787246487100147300,
              "uuid_lslong": 9239711847211676000
            },
            "created": "2017-05-23T05:06:57.289349",
            "description": null,
            "creator": null,
            "user_visible": true,
            "last_modified": "2017-05-23T05:06:57.289349",
            "permissions": {
              "owner": "cloud-admin",
              "owner_access": 7,
              "other_access": 7,
              "group": "cloud-admin-group",
              "group_access": 7
            }
          },
          "fq_name": [
            "default-domain",
            "admin",
            "Label-Label1"
          ],
          "tag_type": "Label"
        }
      },
      {
        "tag": {
          "display_name": "Tier-Middlelayer",
          "uuid": "9a17742e-c1fe-4a33-90b1-b550a44929c8",
          "name": "Tier-Middlelayer",
          "href": "http://10.84.17.3:8082/tag/9a17742e-c1fe-4a33-90b1-b550a44929c8",
          "perms2": {
            "owner": "cloud-admin",
            "owner_access": 7,
            "global_access": 0,
            "share": []
          },
          "tag_value": "Middlelayer",
          "id_perms": {
            "enable": true,
            "uuid": {
              "uuid_mslong": 11103471150477232000,
              "uuid_lslong": 10426313970297678000
            },
            "created": "2017-05-23T11:25:51.465657",
            "description": null,
            "creator": null,
            "user_visible": true,
            "last_modified": "2017-05-23T11:25:51.465657",
            "permissions": {
              "owner": "cloud-admin",
              "owner_access": 7,
              "other_access": 7,
              "group": "cloud-admin-group",
              "group_access": 7
            }
          },
          "tag_id": 268435496,
          "fq_name": [
            "Tier-Middlelayer"
          ],
          "tag_type": "Tier"
        }
      },
      {
        "tag": {
          "display_name": "Application-Finance",
          "uuid": "388e4734-a916-4233-bc6c-112cc7a8ebef",
          "name": "Application-Finance",
          "href": "http://10.84.17.3:8082/tag/388e4734-a916-4233-bc6c-112cc7a8ebef",
          "parent_uuid": "fb339563-f93a-4418-bb4d-62f8d5a11c0b",
          "parent_type": "project",
          "tag_id": 134217765,
          "tag_value": "Finance",
          "perms2": {
            "owner": "cloud-admin",
            "owner_access": 7,
            "global_access": 0,
            "share": []
          },
          "id_perms": {
            "enable": true,
            "uuid": {
              "uuid_mslong": 4075273004317557000,
              "uuid_lslong": 13577245860641171000
            },
            "created": "2017-05-23T05:08:46.014235",
            "description": null,
            "creator": null,
            "user_visible": true,
            "last_modified": "2017-05-23T05:08:46.014235",
            "permissions": {
              "owner": "cloud-admin",
              "owner_access": 7,
              "other_access": 7,
              "group": "cloud-admin-group",
              "group_access": 7
            }
          },
          "fq_name": [
            "default-domain",
            "admin",
            "Application-Finance"
          ],
          "tag_type": "Application"
        }
      },
      {
        "tag": {
          "fq_name": [
            "Application-Blue"
          ],
          "uuid": "3ae4b422-bd63-4cef-9c72-90160c6eb1d9",
          "name": "Application-Blue",
          "href": "http://10.84.17.3:8082/tag/3ae4b422-bd63-4cef-9c72-90160c6eb1d9",
          "perms2": {
            "owner": "cloud-admin",
            "owner_access": 7,
            "global_access": 0,
            "share": []
          },
          "tag_value": "Blue",
          "id_perms": {
            "enable": true,
            "uuid": {
              "uuid_mslong": 4243714810189139000,
              "uuid_lslong": 11273231241634034000
            },
            "created": "2017-05-20T13:45:06.816673",
            "description": null,
            "creator": null,
            "user_visible": true,
            "last_modified": "2017-05-20T13:45:06.816673",
            "permissions": {
              "owner": "cloud-admin",
              "owner_access": 7,
              "other_access": 7,
              "group": "cloud-admin-group",
              "group_access": 7
            }
          },
          "tag_id": 134217736,
          "display_name": "Tag1",
          "tag_type": "Application"
        }
      }
    ]
  }
]
